ssbdplus/__init__.py
ssbdplus/m1.py
ssbdplus/m2.py
ssbdplus/pipeline.py
ssbdplus/prefetch.py
ssbdplus-2.2.0.dist-info/LICENSE
ssbdplus-2.2.0.dist-info/METADATA
ssbdplus-2.2.0.dist-info/WHEEL
ssbdplus-2.2.0.dist-info/top_level.txt
ssbdplus-2.2.0.dist-info/RECORD
