Metadata-Version: 2.1
Name: ssbdplus
Version: 2.2.0
Summary: Models pertaining to the paper, Introducing SSBD+ Dataset with a Convolutional Pipeline for detecting Self-Stimulatory Behaviours in Children using raw videos
Home-page: https://github.com/sarl-iiitb/ssbd-pipeline
Author: SARL, IIITB
Author-email: mr@iiitb.ac.in
Project-URL: Bug Tracker, https://github.com/sarl-iiitb/ssbd-pipeline/issues
Classifier: Programming Language :: Python :: 3
Classifier: License :: OSI Approved :: MIT License
Classifier: Operating System :: OS Independent
Requires-Python: >=3.6
License-File: LICENSE
